Metadata-Version: 2.1
Name: pymysql2
Version: 1.1.1
Summary: Simple and secure module to perform safe MySQL queries
Home-page: https://github.com/AlaBouali/bane
Author: AlaBouali
Author-email: trap.leader.123@gmail.com
License: MIT License
Platform: UNKNOWN
Classifier: Programming Language :: Python
Classifier: License :: OSI Approved :: MIT License 
Requires-Python: >=2.7
